aai/__init__.py
aai_raceychan_test-0.1.0.dist-info/METADATA
aai_raceychan_test-0.1.0.dist-info/WHEEL
aai_raceychan_test-0.1.0.dist-info/RECORD
