Metadata-Version: 2.4
Name: aai-raceychan-test
Version: 0.1.0
Summary: A dummy package for testing PyPI publishing
Author-email: raceychan <raceychan@gmail.com>
Requires-Python: >=3.10
